cubicweb_registration/__init__.py
cubicweb_registration/__pkginfo__.py
cubicweb_registration/site_cubicweb.py
cubicweb_registration/views.py
cubicweb_registration/i18n/en.po
cubicweb_registration/i18n/fr.po
cubicweb_registration/migration/0.7.0_Any.py
cubicweb_registration/migration/postcreate.py
cubicweb_registration-0.14.0.dist-info/METADATA
cubicweb_registration-0.14.0.dist-info/WHEEL
cubicweb_registration-0.14.0.dist-info/entry_points.txt
cubicweb_registration-0.14.0.dist-info/top_level.txt
cubicweb_registration-0.14.0.dist-info/RECORD
