Metadata-Version: 2.1
Name: cubicweb-registration
Version: 0.14.0
Summary: public registration component for the CubicWeb framework
Home-page: https://forge.extranet.logilab.fr/cubicweb/cubes/cubicweb-registration
Author: LOGILAB S.A. (Paris, FRANCE)
Author-email: contact@logilab.fr
License: LGPL
Classifier: Environment :: Web Environment
Classifier: Framework :: CubicWeb
Classifier: Programming Language :: Python :: 3
Classifier: Programming Language :: Python :: 3 :: Only
Classifier: Programming Language :: JavaScript
Requires-Dist: cubicweb[postgresql] <5.0,>=4.0.0
Requires-Dist: cubicweb-web <2.0.0,>=1.1.0
Requires-Dist: cubicweb-forgotpwd
Requires-Dist: Pillow
